{"format": "torch", "nodes": [{"name": "transforms.0", "id": 139782863395664, "class_name": "AffineCoupling(\n  (nn): MLP(\n    (non_linearity): ReLU()\n    (in_layer): Linear(in_features=2, out_features=128, bias=True)\n    (out_layer): Linear(in_features=128, out_features=4, bias=True)\n    (layers): ModuleList(\n      (0): Linear(in_features=128, out_features=128, bias=True)\n      (1): Linear(in_features=128, out_features=128, bias=True)\n    )\n  )\n)", "parameters": [["nn.in_layer.weight", [128, 2]], ["nn.in_layer.bias", [128]], ["nn.out_layer.weight", [4, 128]], ["nn.out_layer.bias", [4]], ["nn.layers.0.weight", [128, 128]], ["nn.layers.0.bias", [128]], ["nn.layers.1.weight", [128, 128]], ["nn.layers.1.bias", [128]]], "output_shape": [[128, 4], [128]], "num_parameters": [256, 128, 512, 4, 16384, 128, 16384, 128]}, {"name": "transforms.1", "id": 139782863330960, "class_name": "ActNormBijectionCloud()", "parameters": [["shift", [1, 4]], ["log_scale", [1, 4]]], "output_shape": [[128, 4], [128]], "num_parameters": [4, 4]}, {"name": "transforms.2", "id": 139782863330320, "class_name": "FullCombiner()", "parameters": [["w", [4, 4]]], "output_shape": [[128, 4], []], "num_parameters": [16]}, {"name": "transforms.3", "id": 139782863327824, "class_name": "AffineCoupling(\n  (nn): MLP(\n    (non_linearity): ReLU()\n    (in_layer): Linear(in_features=2, out_features=128, bias=True)\n    (out_layer): Linear(in_features=128, out_features=4, bias=True)\n    (layers): ModuleList(\n      (0): Linear(in_features=128, out_features=128, bias=True)\n      (1): Linear(in_features=128, out_features=128, bias=True)\n    )\n  )\n)", "parameters": [["nn.in_layer.weight", [128, 2]], ["nn.in_layer.bias", [128]], ["nn.out_layer.weight", [4, 128]], ["nn.out_layer.bias", [4]], ["nn.layers.0.weight", [128, 128]], ["nn.layers.0.bias", [128]], ["nn.layers.1.weight", [128, 128]], ["nn.layers.1.bias", [128]]], "output_shape": [[128, 4], [128]], "num_parameters": [256, 128, 512, 4, 16384, 128, 16384, 128]}, {"name": "transforms.4", "id": 139782863329616, "class_name": "ActNormBijectionCloud()", "parameters": [["shift", [1, 4]], ["log_scale", [1, 4]]], "output_shape": [[128, 4], [128]], "num_parameters": [4, 4]}, {"name": "transforms.5", "id": 139781085722960, "class_name": "FullCombiner()", "parameters": [["w", [4, 4]]], "output_shape": [[128, 4], []], "num_parameters": [16]}, {"name": "transforms.6", "id": 139782863442448, "class_name": "AffineCoupling(\n  (nn): MLP(\n    (non_linearity): ReLU()\n    (in_layer): Linear(in_features=2, out_features=128, bias=True)\n    (out_layer): Linear(in_features=128, out_features=4, bias=True)\n    (layers): ModuleList(\n      (0): Linear(in_features=128, out_features=128, bias=True)\n      (1): Linear(in_features=128, out_features=128, bias=True)\n    )\n  )\n)", "parameters": [["nn.in_layer.weight", [128, 2]], ["nn.in_layer.bias", [128]], ["nn.out_layer.weight", [4, 128]], ["nn.out_layer.bias", [4]], ["nn.layers.0.weight", [128, 128]], ["nn.layers.0.bias", [128]], ["nn.layers.1.weight", [128, 128]], ["nn.layers.1.bias", [128]]], "output_shape": [[128, 4], [128]], "num_parameters": [256, 128, 512, 4, 16384, 128, 16384, 128]}, {"name": "transforms.7", "id": 139782863442640, "class_name": "ActNormBijectionCloud()", "parameters": [["shift", [1, 4]], ["log_scale", [1, 4]]], "output_shape": [[128, 4], [128]], "num_parameters": [4, 4]}, {"name": "transforms.8", "id": 139782863443728, "class_name": "FullCombiner()", "parameters": [["w", [4, 4]]], "output_shape": [[128, 4], []], "num_parameters": [16]}, {"name": "transforms.9", "id": 139782863443792, "class_name": "AffineCoupling(\n  (nn): MLP(\n    (non_linearity): ReLU()\n    (in_layer): Linear(in_features=2, out_features=128, bias=True)\n    (out_layer): Linear(in_features=128, out_features=4, bias=True)\n    (layers): ModuleList(\n      (0): Linear(in_features=128, out_features=128, bias=True)\n      (1): Linear(in_features=128, out_features=128, bias=True)\n    )\n  )\n)", "parameters": [["nn.in_layer.weight", [128, 2]], ["nn.in_layer.bias", [128]], ["nn.out_layer.weight", [4, 128]], ["nn.out_layer.bias", [4]], ["nn.layers.0.weight", [128, 128]], ["nn.layers.0.bias", [128]], ["nn.layers.1.weight", [128, 128]], ["nn.layers.1.bias", [128]]], "output_shape": [[128, 4], [128]], "num_parameters": [256, 128, 512, 4, 16384, 128, 16384, 128]}, {"name": "transforms.10", "id": 139782863443984, "class_name": "ActNormBijectionCloud()", "parameters": [["shift", [1, 4]], ["log_scale", [1, 4]]], "output_shape": [[128, 4], [128]], "num_parameters": [4, 4]}, {"name": "transforms.11", "id": 139782863445072, "class_name": "FullCombiner()", "parameters": [["w", [4, 4]]], "output_shape": [[128, 4], []], "num_parameters": [16]}, {"name": "transforms.12", "id": 139782863445264, "class_name": "AffineCoupling(\n  (nn): MLP(\n    (non_linearity): ReLU()\n    (in_layer): Linear(in_features=2, out_features=128, bias=True)\n    (out_layer): Linear(in_features=128, out_features=4, bias=True)\n    (layers): ModuleList(\n      (0): Linear(in_features=128, out_features=128, bias=True)\n      (1): Linear(in_features=128, out_features=128, bias=True)\n    )\n  )\n)", "parameters": [["nn.in_layer.weight", [128, 2]], ["nn.in_layer.bias", [128]], ["nn.out_layer.weight", [4, 128]], ["nn.out_layer.bias", [4]], ["nn.layers.0.weight", [128, 128]], ["nn.layers.0.bias", [128]], ["nn.layers.1.weight", [128, 128]], ["nn.layers.1.bias", [128]]], "output_shape": [[128, 4], [128]], "num_parameters": [256, 128, 512, 4, 16384, 128, 16384, 128]}], "edges": []}